lndgrpc/__init__.py
lndgrpc/__main__.py
lndgrpc/autopilot.py
lndgrpc/chainnotifier.py
lndgrpc/cli.py
lndgrpc/client.py
lndgrpc/common.py
lndgrpc/dev.py
lndgrpc/errors.py
lndgrpc/invoices.py
lndgrpc/lightning.py
lndgrpc/neutrinokit.py
lndgrpc/peers.py
lndgrpc/router.py
lndgrpc/signer.py
lndgrpc/state.py
lndgrpc/versioner.py
lndgrpc/walletkit.py
lndgrpc/walletunlocker.py
lndgrpc/watchtower.py
lndgrpc/watchtowerclient.py
lndgrpc/aio/__init__.py
lndgrpc/aio/async_client.py
lndgrpc/compiled/autopilot.proto
lndgrpc/compiled/autopilot_pb2.py
lndgrpc/compiled/autopilot_pb2_grpc.py
lndgrpc/compiled/chainkit.proto
lndgrpc/compiled/chainkit_pb2.py
lndgrpc/compiled/chainkit_pb2_grpc.py
lndgrpc/compiled/chainnotifier.proto
lndgrpc/compiled/chainnotifier_pb2.py
lndgrpc/compiled/chainnotifier_pb2_grpc.py
lndgrpc/compiled/dev.proto
lndgrpc/compiled/dev_pb2.py
lndgrpc/compiled/dev_pb2_grpc.py
lndgrpc/compiled/invoices.proto
lndgrpc/compiled/invoices_pb2.py
lndgrpc/compiled/invoices_pb2_grpc.py
lndgrpc/compiled/lightning.proto
lndgrpc/compiled/lightning_pb2.py
lndgrpc/compiled/lightning_pb2_grpc.py
lndgrpc/compiled/lncli.proto
lndgrpc/compiled/lncli_pb2.py
lndgrpc/compiled/lncli_pb2_grpc.py
lndgrpc/compiled/neutrino.proto
lndgrpc/compiled/neutrino_pb2.py
lndgrpc/compiled/neutrino_pb2_grpc.py
lndgrpc/compiled/peers.proto
lndgrpc/compiled/peers_pb2.py
lndgrpc/compiled/peers_pb2_grpc.py
lndgrpc/compiled/router.proto
lndgrpc/compiled/router_pb2.py
lndgrpc/compiled/router_pb2_grpc.py
lndgrpc/compiled/signer.proto
lndgrpc/compiled/signer_pb2.py
lndgrpc/compiled/signer_pb2_grpc.py
lndgrpc/compiled/stateservice.proto
lndgrpc/compiled/stateservice_pb2.py
lndgrpc/compiled/stateservice_pb2_grpc.py
lndgrpc/compiled/verrpc.proto
lndgrpc/compiled/verrpc_pb2.py
lndgrpc/compiled/verrpc_pb2_grpc.py
lndgrpc/compiled/walletkit.proto
lndgrpc/compiled/walletkit_pb2.py
lndgrpc/compiled/walletkit_pb2_grpc.py
lndgrpc/compiled/walletunlocker.proto
lndgrpc/compiled/walletunlocker_pb2.py
lnd_grpc_client-0.6.0.dist-info/METADATA
lnd_grpc_client-0.6.0.dist-info/WHEEL
lnd_grpc_client-0.6.0.dist-info/entry_points.txt
lnd_grpc_client-0.6.0.dist-info/licenses/LICENSE
lnd_grpc_client-0.6.0.dist-info/RECORD
