Metadata-Version: 2.4
Name: lnd-grpc-client
Version: 0.6.0
Summary: An rpc client for LND (lightning network deamon)
Author-email: Kornpow <test@email.com>
License-File: LICENSE
Requires-Python: <4.0,>=3.8.1
Requires-Dist: aiogrpc>=1.8
Requires-Dist: click>=8.1.3
Requires-Dist: googleapis-common-protos>=1.53.0
Requires-Dist: grpcio-tools>=1.37.0
Requires-Dist: grpcio>=1.37.0
Requires-Dist: protobuf3-to-dict>=0.1.5
Requires-Dist: protobuf>=3.15.8
Requires-Dist: ptpython>=3.0.20
Requires-Dist: yachalk>=0.1.5
Provides-Extra: dev
Requires-Dist: sh>=2.0.2; extra == 'dev'
